MANIFEST.in
README.rst
setup.cfg
setup.py
c_builder/__init__.py
c_builder/__version__.py
c_builder/c_file_parser.py
c_builder/c_file_writer.py
c_builder/log.py
c_builder/sample.py
c_builder/utils.py
c_builder.egg-info/PKG-INFO
c_builder.egg-info/SOURCES.txt
c_builder.egg-info/dependency_links.txt
c_builder.egg-info/entry_points.txt
c_builder.egg-info/not-zip-safe
c_builder.egg-info/top_level.txt
c_builder/tests/__init__.py
c_builder/tests/c_test.c
c_builder/tests/c_test_gen.py
c_builder/tests/test_c_builder.py
scripts/run_c_builder.py