Metadata-Version: 1.1
Name: c-builder
Version: 0.0.5
Summary: A tool to read write C file
Home-page: https://github.com/ajbansal/c_builder
Author: Abhijit Bansal
Author-email: pip@abhijitbansal.com
License: MIT
Keywords: testing c_builder C
Platform: UNKNOWN
Classifier: Development Status :: 3 - Alpha
Classifier: License :: OSI Approved :: MIT License
Classifier: Programming Language :: Python :: 3.6
Classifier: Topic :: Software Development :: Code Generators
